electricTortoise/__init__.py
electricTortoise-0.0.1.dist-info/LICENSE
electricTortoise-0.0.1.dist-info/METADATA
electricTortoise-0.0.1.dist-info/WHEEL
electricTortoise-0.0.1.dist-info/top_level.txt
electricTortoise-0.0.1.dist-info/RECORD
