Metadata-Version: 2.1
Name: electricTortoise
Version: 0.0.1
Summary: This package helps determine optimal thrust profiles for space electric propulsion applications. 
Home-page: https://github.com/dev10110/electricTortoise
Author: Devansh R Agrawal
Author-email: devanshinspace@gmail.com
License: MIT
Download-URL: https://github.com/user/reponame/archive/v_01.tar.gz
Keywords: Electric Propulsion,Optimal Control,Preliminary Design
Platform: UNKNOWN
Classifier: Programming Language :: Python :: 3
Classifier: License :: OSI Approved :: MIT License
Classifier: Operating System :: OS Independent
